actain/__init__.py
actain/connector.py
actain/dialect.py
pyactain-0.0.3.dist-info/LICENSE.txt
pyactain-0.0.3.dist-info/METADATA
pyactain-0.0.3.dist-info/WHEEL
pyactain-0.0.3.dist-info/entry_points.txt
pyactain-0.0.3.dist-info/top_level.txt
pyactain-0.0.3.dist-info/RECORD
